azure/mgmt/storagemover/__init__.py
azure/mgmt/storagemover/_client.py
azure/mgmt/storagemover/_configuration.py
azure/mgmt/storagemover/_patch.py
azure/mgmt/storagemover/_version.py
azure/mgmt/storagemover/py.typed
azure/mgmt/storagemover/_utils/__init__.py
azure/mgmt/storagemover/_utils/model_base.py
azure/mgmt/storagemover/_utils/serialization.py
azure/mgmt/storagemover/aio/__init__.py
azure/mgmt/storagemover/aio/_client.py
azure/mgmt/storagemover/aio/_configuration.py
azure/mgmt/storagemover/aio/_patch.py
azure/mgmt/storagemover/aio/operations/__init__.py
azure/mgmt/storagemover/aio/operations/_operations.py
azure/mgmt/storagemover/aio/operations/_patch.py
azure/mgmt/storagemover/models/__init__.py
azure/mgmt/storagemover/models/_enums.py
azure/mgmt/storagemover/models/_models.py
azure/mgmt/storagemover/models/_patch.py
azure/mgmt/storagemover/operations/__init__.py
azure/mgmt/storagemover/operations/_operations.py
azure/mgmt/storagemover/operations/_patch.py
azure_mgmt_storagemover-3.0.0.dist-info/licenses/LICENSE
azure_mgmt_storagemover-3.0.0.dist-info/METADATA
azure_mgmt_storagemover-3.0.0.dist-info/WHEEL
azure_mgmt_storagemover-3.0.0.dist-info/top_level.txt
azure_mgmt_storagemover-3.0.0.dist-info/RECORD
